creyPY/__init__.py
creyPY/helpers.py
creyPY/const/__init__.py
creyPY/const/groups.py
creyPY/const/i18n.py
creyPY/const/stripe.py
creyPY/fastapi/__init__.py
creyPY/fastapi/app.py
creyPY/fastapi/crud.py
creyPY/fastapi/order_by.py
creyPY/fastapi/pagination.py
creyPY/fastapi/testing.py
creyPY/fastapi/testing_async.py
creyPY/fastapi/db/__init__.py
creyPY/fastapi/db/async_session.py
creyPY/fastapi/db/common.py
creyPY/fastapi/db/helpers.py
creyPY/fastapi/db/session.py
creyPY/fastapi/models/__init__.py
creyPY/fastapi/models/base.py
creyPY/fastapi/schemas/__init__.py
creyPY/fastapi/schemas/base.py
creyPY/services/__init__.py
creyPY/services/auth0/__init__.py
creyPY/services/auth0/common.py
creyPY/services/auth0/exceptions.py
creyPY/services/auth0/manage.py
creyPY/services/auth0/utils.py
creyPY-3.0.0.dist-info/LICENSE
creyPY-3.0.0.dist-info/METADATA
creyPY-3.0.0.dist-info/WHEEL
creyPY-3.0.0.dist-info/top_level.txt
creyPY-3.0.0.dist-info/RECORD
